kunkun/__init__.py
kunkun-1.0.dist-info/METADATA
kunkun-1.0.dist-info/WHEEL
kunkun-1.0.dist-info/top_level.txt
kunkun-1.0.dist-info/RECORD
