Metadata-Version: 2.1
Name: kunkun
Version: 1.0
Summary: 这是第一个对外发布的模块，测试哦
Author: gaoqi
Author-email: gaoqi110@163.com
